{"w1": [["ullus", 2.62], ["nullus", 1.91]], "w2": [["sine", 2.75], ["ullus", 2.6], ["nullus", 2.08], ["lex", 1.91]], "w3": [["sine", 2.71], ["ullus", 2.58], ["nullus", 2.46], ["lex", 2.35], ["cum2", 2.02]], "w4": [["sine", 2.68], ["ullus", 2.56], ["lex", 2.53], ["nullus", 2.41], ["ago", 1.98], ["cum2", 1.8]], "w6": [["lex", 2.86], ["ullus", 2.71], ["sine", 2.62], ["nullus", 2.32], ["cum2", 2.12], ["postulo", 1.95], ["ille", 1.9], ["ago", 1.88]], "w8": [["lex", 3.0], ["ullus", 2.87], ["sine", 2.58], ["nullus", 2.25], ["postulo", 2.18], ["omnis", 2.15], ["cum2", 1.86], ["de", 1.83], ["ne", 1.83], ["ago", 1.8]], "r1": {}, "r2": [["ullus", 2.59]], "r3": [["ullus", 3.65], ["sine", 2.96], ["nullus", 2.71], ["personaris", 2.45], ["addo", 2.38], ["sub", 2.07], ["lex", 2.04]], "r4": [["ullus", 4.35], ["sine", 3.99], ["nullus", 3.5], ["lex", 3.24], ["personaris", 3.0], ["addo", 2.9], ["sub", 2.61], ["communio1", 2.41], ["extra", 2.4], ["ago", 2.18]], "r6": [["ullus", 5.54], ["sine", 5.28], ["lex", 4.89], ["nullus", 4.22], ["personaris", 3.6], ["addo", 3.29], ["ago", 3.24], ["communio1", 3.1], ["extra", 3.08], ["sub", 2.98], ["nisi", 2.71], ["postulo", 2.5], ["qui1", 2.28], ["monogamiae", 2.23], ["purifico", 2.23], ["caueri", 2.23], ["quaestuosus", 2.23], ["finitio", 2.23], ["iniussus2", 2.23], ["uoluntas", 2.23], ["usitor", 2.22], ["al", 2.2], ["excludo", 2.19], ["polliceor", 2.18], ["quia", 2.11], ["hora", 2.1], ["uictoria", 2.06], ["taceo", 2.05], ["praetor", 2.04], ["laudo", 2.02]], "r8": [["ullus", 6.52], ["sine", 6.31], ["lex", 5.68], ["personaris", 3.86], ["communio1", 3.66], ["addo", 3.5], ["extra", 3.35], ["sub", 3.17], ["quia", 3.05], ["postulo", 2.97], ["uoluntas", 2.89], ["praeter", 2.84], ["peto", 2.75], ["permitto", 2.65], ["purifico", 2.64], ["caueri", 2.64], ["quaestuosus", 2.64], ["finitio", 2.64], ["iniussus2", 2.64], ["ad-scribo", 2.59], ["al", 2.59], ["excludo", 2.58], ["polliceor", 2.56], ["hora", 2.46], ["ueneo", 2.45], ["certor", 2.44], ["usitor", 2.43], ["luxuriosus", 2.43], ["taceo", 2.42], ["interdictum", 2.42], ["uictoria", 2.42], ["qui1", 2.4], ["corrigo", 2.39], ["laudo", 2.37], ["tego", 2.33], ["ueto", 2.33], ["n", 2.32], ["tollo", 2.31], ["reus", 2.28], ["monogamiae", 2.23], ["mattus", 2.23], ["caput", 2.22], ["episcopus", 2.22], ["rectus", 2.2], ["incurro", 2.2], ["pertimesco", 2.19], ["uinco", 2.19], ["fides", 2.19], ["tolero", 2.17], ["perspicuus", 2.16], ["praetor", 2.16], ["consilium", 2.14], ["uinum", 2.1], ["unde", 2.08], ["apud", 2.06], ["labor", 2.04], ["fingo", 2.04], ["opera", 2.03], ["deinde", 2.01], ["constituo", 2.01], ["necessitas", 2.01], ["tueor", 2.0]], "r12": [["ullus", 7.57], ["communio1", 4.58], ["uoluntas", 4.03], ["personaris", 3.98], ["ad-scribo", 3.82], ["permitto", 3.8], ["peto", 3.79], ["addo", 3.5], ["postulo", 3.34], ["purifico", 3.31], ["caueri", 3.31], ["macellum", 3.31], ["iniussus2", 3.3], ["praeter", 3.3], ["occupatio", 3.28], ["constituo", 3.27], ["patior", 3.27], ["al", 3.25], ["consilium", 3.2], ["caput", 3.16], ["aliquaris", 3.16], ["certor", 3.15], ["interdictum", 3.13], ["corrigo", 3.09], ["hora", 3.08], ["iubeo", 3.07], ["polliceor", 3.05], ["taceo", 3.04], ["ueto", 3.01], ["ueneo", 3.0], ["quaestuosus", 2.99], ["ecqui", 2.98], ["laudo", 2.96], ["pertimesco", 2.94], ["perspicuus", 2.91], ["accido1", 2.84], ["n", 2.84], ["labor", 2.84], ["trado", 2.84], ["finitio", 2.82], ["fides", 2.8], ["praetextatus", 2.8], ["con-pello", 2.8], ["circumspicio", 2.78], ["reus", 2.77], ["fortuna", 2.77], ["opera", 2.76], ["tolero", 2.75], ["sub", 2.74], ["excludo", 2.73], ["tego", 2.66], ["esus2", 2.64], ["colluo", 2.63], ["istinc", 2.63], ["petitor", 2.63], ["extra", 2.62], ["luxuriosus", 2.61], ["auditor", 2.57], ["necessitas", 2.54], ["unde", 2.53], ["rectus", 2.49], ["uictoria", 2.49], ["honor", 2.46], ["rursus", 2.46], ["mattus", 2.43], ["usitor", 2.42], ["gratia", 2.41], ["ar", 2.4], ["mater", 2.39], ["oro", 2.39], ["continuus", 2.39], ["uter", 2.39], ["fingo", 2.38], ["utique", 2.37], ["tollo", 2.34], ["curatio", 2.33], ["adhibeo", 2.27], ["uinum", 2.27], ["uiuo", 2.26], ["monogamiae", 2.23], ["episcopus", 2.21], ["apis1", 2.18], ["incurro", 2.17], ["regnum", 2.15], ["funus", 2.11], ["que", 2.11], ["necesse", 2.07], ["firmo", 2.07], ["exinde", 2.07], ["ter", 2.06], ["recedo", 2.03], ["probo", 2.02], ["destino", 2.02], ["includo", 2.01], ["poena", 2.0]], "r16": [["ullus", 8.46], ["communio1", 5.34], ["uoluntas", 5.31], ["ad-scribo", 4.29], ["patior", 4.17], ["personaris", 3.98], ["accido1", 3.93], ["purifico", 3.87], ["caueri", 3.86], ["permitto", 3.86], ["al", 3.8], ["fortuna", 3.78], ["certor", 3.73], ["occupatio", 3.7], ["interdictum", 3.7], ["constituo", 3.69], ["corrigo", 3.66], ["polliceor", 3.61], ["uter", 3.6], ["macellum", 3.59], ["ueto", 3.58], ["pertimesco", 3.54], ["labor", 3.48], ["laudo", 3.47], ["praeter", 3.46], ["trado", 3.44], ["taceo", 3.42], ["caput", 3.39], ["perspicuus", 3.37], ["opera", 3.35], ["istinc", 3.3], ["iniussus2", 3.3], ["ecqui", 3.3], ["amicus", 3.24], ["fides", 3.2], ["reus", 3.2], ["addo", 3.09], ["iustus", 3.08], ["colluo", 2.99], ["petitor", 2.98], ["mater", 2.96], ["apis1", 2.94], ["extra", 2.92], ["adhibeo", 2.92], ["auditor", 2.92], ["firmo", 2.83], ["que", 2.83], ["signaculum", 2.82], ["iudaicae", 2.82], ["castimonia", 2.82], ["esus2", 2.82], ["de_-sisto", 2.81], ["finitio", 2.81], ["regnum", 2.8], ["honor", 2.79], ["praetextatus", 2.79], ["con-pello", 2.79], ["n", 2.79], ["includo", 2.78], ["mobilis", 2.77], ["cottidie", 2.77], ["circumspicio", 2.76], ["postulo", 2.76], ["continuus", 2.76], ["remoueo", 2.75], ["oro", 2.71], ["curatio", 2.7], ["excludo", 2.7], ["hora", 2.66], ["uiuo", 2.63], ["accumbo", 2.62], ["sa", 2.62], ["luxuriosus", 2.6], ["destino", 2.6], ["prior", 2.57], ["rursus", 2.54], ["sub", 2.52], ["christus", 2.51], ["scriptor", 2.46], ["cibus", 2.46], ["necessitas", 2.46], ["ter", 2.45], ["iunctio", 2.45], ["utique", 2.44], ["disertor", 2.44], ["mattus", 2.43], ["usitor", 2.41], ["unde", 2.39], ["rectus", 2.39], ["ar", 2.39], ["uictoria", 2.39], ["armo", 2.38], ["superstitio", 2.38], ["dominus", 2.36], ["gratia", 2.36], ["dens", 2.35], ["desino", 2.35], ["saepe", 2.3], ["ergo", 2.29], ["fingo", 2.29], ["coepio", 2.28], ["disciplina", 2.27], ["adiuuo", 2.24], ["monogamiae", 2.23], ["ueneo", 2.23], ["quaestuosus", 2.22], ["feriae", 2.22], ["episcopus", 2.21], ["factor", 2.18], ["tollo", 2.18], ["interdico", 2.18], ["abstinentia", 2.15], ["postea", 2.15], ["integritas", 2.13], ["titulis", 2.13], ["pecunia", 2.11], ["tolero", 2.11], ["uinum", 2.08], ["probo", 2.08], ["funus", 2.07], ["argumentum", 2.03], ["remedium", 2.02], ["aperio", 2.01], ["exinde", 2.01], ["lego", 2.01]]}