{"w1": [["is", 2.44], ["pondus", 1.98]], "w2": [["is", 1.99], ["dimidio", 1.99], ["latitudo", 1.99], ["pondus", 1.97], ["dico", 1.85], ["do", 1.82]], "w3": [["is", 2.6], ["dimidio", 2.44], ["latitudo", 2.22], ["dico", 2.09], ["dimidium", 1.99], ["totus", 1.98], ["pondus", 1.95], ["ad", 1.86], ["liber", 1.83]], "w4": [["dimidio", 3.45], ["totus", 2.57], ["is", 2.53], ["dico", 2.51], ["dimidium", 2.44], ["latitudo", 2.21], ["liber", 2.04], ["do", 2.0], ["sextarius", 1.99], ["pondus", 1.94], ["huc", 1.92]], "w6": [["dimidio", 3.59], ["totus", 2.67], ["dico", 2.6], ["dimidium", 2.44], ["is", 2.37], ["liber", 2.21], ["latitudo", 2.21], ["do", 2.01], ["sextarius", 1.99], ["pondus", 1.91], ["huc", 1.89], ["sumo", 1.83], ["efficio", 1.83]], "w8": [["dimidio", 3.86], ["dimidium", 2.82], ["totus", 2.77], ["dico", 2.56], ["latitudo", 2.42], ["is", 2.35], ["cyathus", 2.21], ["liber", 2.15], ["do", 2.06], ["dimidia", 1.99], ["sextarius", 1.98], ["iugerum", 1.98], ["spatium", 1.9], ["pondus", 1.9], ["huc", 1.87], ["ad", 1.81]], "r1": {}, "r2": {}, "r3": [["pondus", 2.78], ["latitudo", 2.62], ["dimidio", 2.43], ["crassitudo", 2.21], ["sumo", 2.11]], "r4": [["pondus", 3.54], ["dimidio", 3.45], ["latitudo", 3.29], ["foramen", 2.62], ["crassitudo", 2.62], ["sumo", 2.48], ["cyathus", 2.42], ["liber", 2.33], ["galla1", 2.22], ["sextarius", 2.22], ["denarius", 2.21], ["iugerum", 2.21], ["digitus1", 2.2], ["spatium", 2.13], ["do", 2.12]], "r6": [["dimidio", 5.55], ["pondus", 4.5], ["latitudo", 3.82], ["sextarius", 3.58], ["liber", 3.17], ["denarius", 2.97], ["crassitudo", 2.95], ["totus", 2.91], ["spatium", 2.86], ["galla1", 2.81], ["iugerum", 2.79], ["cyathus", 2.78], ["foramen", 2.78], ["digitus1", 2.78], ["fabula", 2.76], ["sumo", 2.73], ["decoquo", 2.7], ["scyphus", 2.64], ["tero", 2.46], ["scripulis", 2.45], ["obsonium", 2.44], ["digitus", 2.38], ["efficio", 2.3], ["hypate", 2.23], ["porcellus", 2.23], ["hemitonium", 2.23], ["mercurium", 2.23], ["perforo", 2.22], ["stipes", 2.22], ["dimidia", 2.22], ["gallinaceus", 2.21], ["obolus", 2.21], ["procurro", 2.21], ["sudo", 2.2], ["axis", 2.2], ["resina", 2.19], ["mensura", 2.18], ["paruus", 2.18], ["septimus", 2.17], ["insum", 2.11], ["substantia", 2.09], ["argentum", 2.06], ["familia", 2.06], ["diuido", 2.03], ["iuppiter", 2.0]], "r8": [["dimidio", 6.37], ["pondus", 5.08], ["sextarius", 4.66], ["latitudo", 3.93], ["liber", 3.83], ["denarius", 3.57], ["scyphus", 3.46], ["spatium", 3.43], ["fabula", 3.38], ["decoquo", 3.3], ["crassitudo", 3.25], ["totus", 3.24], ["galla1", 3.14], ["iugerum", 3.12], ["dimidia", 2.98], ["tero", 2.94], ["cyathus", 2.94], ["efficio", 2.9], ["sumo", 2.79], ["foramen", 2.76], ["digitus1", 2.76], ["aqua", 2.75], ["longitudo", 2.73], ["promitto", 2.67], ["scripulis", 2.64], ["hypate", 2.64], ["sucus", 2.64], ["porcellus", 2.64], ["mercurium", 2.64], ["balineo", 2.64], ["argentum", 2.64], ["perforo", 2.63], ["gallinaceus", 2.62], ["obolus", 2.62], ["sudo", 2.6], ["resina", 2.58], ["mensura", 2.58], ["tres", 2.57], ["digitus", 2.56], ["substantia", 2.46], ["protagoras", 2.45], ["hemitonium", 2.44], ["acacia", 2.44], ["terebinthinus", 2.43], ["purgatio", 2.43], ["uersus", 2.43], ["stipes", 2.42], ["xxu", 2.42], ["familia", 2.42], ["uiiii", 2.42], ["quadraginta", 2.41], ["iuppiter", 2.38], ["misceo", 2.36], ["septimus", 2.36], ["misericordia", 2.34], ["simplex", 2.32], ["albus", 2.31], ["duo", 2.3], ["quantus", 2.29], ["insum", 2.29], ["offertor", 2.29], ["summus", 2.27], ["fundo1", 2.25], ["cxu", 2.23], ["porcina", 2.23], ["cinis", 2.23], ["spira", 2.23], ["sapa", 2.23], ["excreatio", 2.23], ["obsonium", 2.22], ["sorbeo", 2.21], ["xiii", 2.2], ["procurro", 2.2], ["comburo", 2.19], ["axis", 2.19], ["alienus", 2.18], ["priusquam", 2.17], ["portio", 2.16], ["dissoluo", 2.15], ["disto", 2.14], ["paulum", 2.12], ["reliquus", 2.09], ["pecco", 2.08], ["medeor", 2.08], ["quintus1", 2.07], ["mundus", 2.07], ["fere", 2.05], ["iterum", 2.03], ["os", 2.01], ["donec", 2.01]], "r12": [["dimidio", 7.58], ["sextarius", 6.45], ["pondus", 5.93], ["decoquo", 4.73], ["liber", 4.59], ["dimidia", 4.56], ["denarius", 4.53], ["spatium", 4.47], ["fabula", 4.25], ["cyathus", 4.05], ["latitudo", 4.02], ["promitto", 3.95], ["aqua", 3.86], ["sucus", 3.67], ["scyphus", 3.59], ["uersus", 3.49], ["balineo", 3.46], ["quadraginta", 3.42], ["priusquam", 3.39], ["uinum", 3.37], ["cinis", 3.37], ["mulceo", 3.36], ["porcellus", 3.31], ["mercurium", 3.31], ["perforo", 3.29], ["gallinaceus", 3.28], ["luna", 3.26], ["sudo", 3.26], ["mille", 3.24], ["resina", 3.24], ["mensura", 3.23], ["argentum", 3.23], ["longitudo", 3.18], ["pecco", 3.16], ["protagoras", 3.16], ["acacia", 3.16], ["efficio", 3.15], ["disco", 3.14], ["terebinthinus", 3.14], ["xxu", 3.13], ["reliquus", 3.12], ["iugerum", 3.09], ["triginta", 3.07], ["crassitudo", 3.05], ["familia", 3.02], ["simplex", 3.0], ["albus", 3.0], ["addo", 3.0], ["porcina", 2.99], ["excreatio", 2.99], ["iuppiter", 2.99], ["galla1", 2.97], ["statim", 2.96], ["misceo", 2.95], ["comburo", 2.95], ["fundo1", 2.91], ["tunc", 2.9], ["dissoluo", 2.89], ["tres", 2.88], ["tero", 2.82], ["medeor", 2.82], ["saturnus", 2.79], ["quini", 2.78], ["paciscor", 2.78], ["offertor", 2.78], ["pondo", 2.77], ["iterum", 2.76], ["sextus1", 2.76], ["minae", 2.74], ["portio", 2.74], ["uirga", 2.74], ["substantia", 2.73], ["alienus", 2.72], ["sordidus", 2.7], ["bini", 2.65], ["sanguis", 2.64], ["spira", 2.63], ["dysintericis", 2.62], ["cornus1", 2.6], ["coquo", 2.6], ["ficus", 2.6], ["hemina1", 2.59], ["fundo", 2.57], ["potio2", 2.56], ["duplex", 2.53], ["os", 2.53], ["lauo", 2.52], ["studiosus", 2.49], ["simul", 2.49], ["misericordia", 2.48], ["grandis", 2.45], ["purgatio", 2.42], ["quindecim", 2.41], ["quingenti", 2.41], ["bubulus", 2.41], ["uiiii", 2.4], ["obolus", 2.4], ["tempestas", 2.39], ["sumo", 2.37], ["arbor1", 2.36], ["fugio", 2.36], ["uetustus", 2.35], ["compono", 2.33], ["septimus", 2.31], ["taurus", 2.3], ["peto", 2.27], ["dominus", 2.26], ["sicco", 2.25], ["relinquo", 2.24], ["sol", 2.24], ["pono", 2.24], ["pecunia", 2.24], ["coclearium", 2.23], ["murinus", 2.23], ["sapa", 2.22], ["hesiodus", 2.22], ["qualibet", 2.22], ["obsonium", 2.21], ["lentiscus", 2.21], ["lamina", 2.2], ["qui1", 2.2], ["bibo1", 2.2], ["confinis", 2.19], ["castrensis", 2.19], ["sorbeo", 2.19], ["insum", 2.19], ["no1", 2.18], ["nimis", 2.18], ["xiii", 2.18], ["procurro", 2.18], ["uenus", 2.16], ["mox", 2.16], ["summus", 2.15], ["donec", 2.12], ["foramen", 2.1], ["mundus", 2.09], ["farina", 2.09], ["spargo1", 2.08], ["merces", 2.08], ["terni", 2.06]], "r16": [["dimidio", 8.26], ["sextarius", 7.58], ["pondus", 6.22], ["dimidia", 5.55], ["decoquo", 5.11], ["denarius", 5.05], ["spatium", 4.94], ["fabula", 4.89], ["mille", 4.65], ["uinum", 4.62], ["promitto", 4.62], ["luna", 4.28], ["addo", 4.26], ["resina", 4.05], ["latitudo", 4.0], ["quadraginta", 3.95], ["priusquam", 3.92], ["cyathus", 3.92], ["sucus", 3.9], ["cinis", 3.88], ["porcellus", 3.87], ["mercurium", 3.86], ["uersus", 3.83], ["hemina1", 3.83], ["gallinaceus", 3.83], ["fundo", 3.81], ["longitudo", 3.74], ["protagoras", 3.74], ["acacia", 3.73], ["terebinthinus", 3.72], ["reliquus", 3.7], ["triginta", 3.65], ["disco", 3.64], ["mulceo", 3.62], ["simonidi", 3.6], ["sescuplus", 3.6], ["porcina", 3.6], ["tonus", 3.6], ["scyphus", 3.59], ["quingenti", 3.57], ["comburo", 3.55], ["familia", 3.55], ["iuppiter", 3.52], ["misceo", 3.5], ["fundo1", 3.47], ["statim", 3.46], ["balineo", 3.45], ["saturnus", 3.43], ["quini", 3.42], ["paciscor", 3.41], ["sudo", 3.4], ["pondo", 3.4], ["tunc", 3.39], ["sextus1", 3.39], ["iugerum", 3.39], ["uirga", 3.37], ["sordidus", 3.33], ["efficio", 3.31], ["dysintericis", 3.3], ["bini", 3.3], ["cornus1", 3.27], ["ficus", 3.27], ["potio2", 3.23], ["lauo", 3.19], ["argentum", 3.17], ["perforo", 3.13], ["bubulus", 3.12], ["pecco", 3.12], ["grandis", 3.12], ["arbor1", 3.08], ["uetustus", 3.06], ["mensura", 3.06], ["tempestas", 3.05], ["contractus2", 3.0], ["coclearium", 2.99], ["excreatio", 2.98], ["lamina", 2.97], ["galla1", 2.96], ["simplex", 2.96], ["castrensis", 2.95], ["tero", 2.94], ["bibo1", 2.92], ["coquo", 2.91], ["nimis", 2.9], ["uenus", 2.89], ["crassitudo", 2.86], ["dissoluo", 2.86], ["spargo1", 2.85], ["merces", 2.85], ["sol", 2.82], ["pollucem", 2.82], ["hora", 2.81], ["pecunia", 2.8], ["medeor", 2.78], ["mundus", 2.77], ["candeo", 2.75], ["portio", 2.72], ["minae", 2.72], ["offertor", 2.71], ["duplex", 2.7], ["iterum", 2.7], ["sanguis", 2.67], ["substantia", 2.67], ["studiosus", 2.64], ["stibium", 2.64], ["spira", 2.63], ["nummus", 2.63], ["dis-iacio", 2.61], ["utilis", 2.61], ["xxu", 2.6], ["carmen", 2.59], ["alienus", 2.57], ["oleum", 2.57], ["octauus", 2.56], ["ferreus", 2.55], ["altitudo", 2.55], ["matutinus", 2.53], ["mando1", 2.52], ["inde", 2.5], ["farina", 2.5], ["militaris", 2.47], ["dimitto", 2.46], ["fugio", 2.46], ["compono", 2.46], ["misericordia", 2.44], ["murinus", 2.44], ["sae", 2.43], ["sedecim", 2.42], ["albus", 2.41], ["panis", 2.41], ["quindecim", 2.4], ["reperio", 2.4], ["signifer", 2.4], ["tres", 2.37], ["no1", 2.34], ["africa", 2.34], ["simul", 2.32], ["qui1", 2.31], ["curo", 2.3], ["septimus", 2.27], ["taurus", 2.27], ["emineo", 2.25], ["myrtites", 2.23], ["sapa", 2.22], ["hesiodus", 2.22], ["praecoquo", 2.22], ["laxamentum", 2.22], ["sumo", 2.22], ["qualibet", 2.21], ["obsonium", 2.2], ["lentiscus", 2.2], ["tertio2", 2.2], ["hysopum", 2.19], ["item", 2.19], ["castor", 2.19], ["confinis", 2.18], ["sorbeo", 2.18], ["xiii", 2.16], ["absum", 2.16], ["procurro", 2.16], ["acerbus", 2.16], ["iuro", 2.16], ["os", 2.14], ["paulus", 2.13], ["insum", 2.12], ["leuis", 2.1], ["dominus", 2.08], ["uolo1", 2.07], ["aequus", 2.05], ["claudus", 2.05], ["mox", 2.04], ["terni", 2.02], ["relinquo", 2.0]]}