{"w1": {}, "w2": {}, "w3": {}, "w4": {}, "w6": {}, "w8": {}, "r1": {}, "r2": {}, "r3": {}, "r4": [["libido", 2.22]], "r6": [["libido", 2.62], ["sacrilega", 2.24], ["prex", 2.22], ["utrum", 2.21], ["poena", 2.19], ["caesar", 2.14], ["puto", 2.05]], "r8": [["libido", 2.79], ["sacrilega", 2.65], ["caesar", 2.53], ["secta", 2.45], ["caleo", 2.44], ["punior", 2.44], ["uotum", 2.43], ["prex", 2.43], ["monstruosus", 2.23], ["feruo", 2.23], ["clamito", 2.23], ["sacerdos1", 2.23], ["puto", 2.22], ["crudelis", 2.22], ["conuiuium", 2.21], ["utrum", 2.21], ["promitto", 2.2], ["diuido", 2.19], ["poena", 2.18], ["mors", 2.09]], "r12": [["libido", 3.42], ["sacrilega", 3.16], ["punior", 3.15], ["feruo", 3.0], ["mors", 2.86], ["monstruosus", 2.83], ["exardeo", 2.83], ["concupisco", 2.82], ["clamito", 2.64], ["caleo", 2.64], ["canis", 2.61], ["frequens", 2.61], ["caesar", 2.49], ["masculus", 2.44], ["exaudio", 2.44], ["dius", 2.43], ["uotum", 2.43], ["prex", 2.42], ["immortalis", 2.42], ["narro", 2.42], ["conuiuium", 2.41], ["candelabrum", 2.23], ["secta", 2.23], ["christianus", 2.23], ["cito", 2.22], ["crudelis", 2.21], ["propior", 2.13]], "r16": [["libido", 3.42], ["concupisco", 3.31], ["punior", 3.31], ["mors", 3.19], ["sacrilega", 3.16], ["candelabrum", 3.0], ["exardeo", 3.0], ["feruo", 3.0], ["canis", 2.97], ["propior", 2.92], ["monstruosus", 2.83], ["necto", 2.82], ["uxor", 2.75], ["caleo", 2.64], ["clamito", 2.64], ["tendo", 2.62], ["frequens", 2.61], ["poena", 2.58], ["caesar", 2.49], ["iactus", 2.45], ["masculus", 2.44], ["adultero", 2.44], ["exaudio", 2.44], ["subduco", 2.44], ["cito", 2.43], ["dius", 2.43], ["uotum", 2.42], ["prex", 2.42], ["immortalis", 2.42], ["conuiuium", 2.41], ["oculus", 2.28], ["offula", 2.23]]}