{"w1": [["cestus1", 6.48], ["aeneas", 5.18], ["tus", 3.56], ["uotum", 3.39], ["sae", 3.0], ["tam", 2.99], ["cura", 2.93], ["antoninus", 2.82], ["turba", 2.72], ["mater", 2.52], ["marcus1", 2.4], ["tum", 2.34], ["quisque", 2.33], ["iustus", 2.29], ["pater", 2.29], ["munus", 2.25], ["os", 2.19], ["fleo", 2.11], ["at", 2.08], ["nascor", 2.08], ["sancio", 2.07], ["sacer", 2.05], ["metellus", 1.96], ["tu", 1.92], ["uates", 1.91], ["uerbum", 1.88], ["frater", 1.87], ["filia", 1.84], ["soror", 1.83], ["numen", 1.83]], "w2": [["cestus1", 6.47], ["aeneas", 5.25], ["marcus1", 4.18], ["uotum", 3.75], ["tus", 3.52], ["mater", 3.44], ["cura", 3.05], ["sae", 2.99], ["antoninus", 2.98], ["tam", 2.89], ["pater", 2.82], ["nascor", 2.79], ["iustus", 2.76], ["turba", 2.63], ["metellus", 2.59], ["uates", 2.52], ["sacer", 2.34], ["parens", 2.28], ["frater", 2.28], ["os", 2.23], ["filia", 2.19], ["scelero", 2.18], ["manes", 2.16], ["quisque", 2.09], ["tu", 2.09], ["munus", 2.07], ["imperator", 2.07], ["gener", 2.03], ["diuus", 2.01], ["fleo", 2.0], ["appello", 1.98], ["antoninum", 1.97], ["tum", 1.97], ["numen", 1.94], ["sancio", 1.92], ["manus", 1.91], ["gratus", 1.89], ["do", 1.88], ["maestus", 1.87], ["impius", 1.86], ["poeta", 1.83], ["prex", 1.83], ["placidus", 1.82]], "w3": [["cestus1", 6.47], ["aeneas", 5.24], ["marcus1", 4.39], ["mater", 4.06], ["uotum", 3.69], ["tus", 3.63], ["pater", 3.58], ["iustus", 3.46], ["cura", 3.04], ["sae", 2.99], ["antoninus", 2.97], ["nascor", 2.91], ["parens", 2.9], ["turba", 2.73], ["tam", 2.7], ["impius", 2.69], ["uates", 2.65], ["frater", 2.65], ["pius", 2.57], ["metellus", 2.57], ["prex", 2.46], ["antonini", 2.41], ["scelero", 2.37], ["os", 2.33], ["officium", 2.31], ["numen", 2.29], ["fortis", 2.27], ["sacer", 2.21], ["antoninum", 2.2], ["mereo", 2.19], ["gener", 2.18], ["diuus", 2.15], ["imperator", 2.14], ["manes", 2.13], ["seruo", 2.11], ["filia", 2.08], ["coniunx", 2.08], ["soror", 2.07], ["do", 2.01], ["amoenus", 1.94], ["felix", 1.94], ["parco", 1.92], ["cor", 1.92], ["q", 1.92], ["munus", 1.91], ["fleo", 1.89], ["nepos", 1.84], ["unicus", 1.83], ["maestus", 1.81], ["filius", 1.81]], "w4": [["cestus1", 6.47], ["aeneas", 5.22], ["marcus1", 4.7], ["mater", 4.62], ["pater", 4.01], ["uotum", 3.91], ["tus", 3.73], ["iustus", 3.53], ["parens", 3.27], ["cura", 3.05], ["sae", 2.99], ["uates", 2.97], ["antoninus", 2.96], ["antonini", 2.78], ["nascor", 2.72], ["turba", 2.66], ["impius", 2.65], ["tam", 2.56], ["metellus", 2.54], ["pius", 2.5], ["frater", 2.47], ["soror", 2.41], ["prex", 2.41], ["officium", 2.38], ["scelero", 2.35], ["fortis", 2.33], ["sacer", 2.31], ["cor", 2.3], ["q", 2.3], ["diuus", 2.3], ["os", 2.26], ["mereo", 2.24], ["antoninum", 2.19], ["numen", 2.19], ["gratus", 2.12], ["gener", 2.1], ["manes", 2.1], ["augustus", 2.09], ["nepos", 2.05], ["fleo", 2.05], ["do", 2.04], ["munus", 2.01], ["imperator", 2.0], ["filia", 1.99], ["coniunx", 1.98], ["seruo", 1.97], ["sto", 1.97], ["sancio", 1.93], ["umbra", 1.93], ["amoenus", 1.92], ["adopto", 1.91], ["iuuenis", 1.86], ["felix", 1.86], ["ueneror", 1.85], ["parco", 1.84]], "w6": [["cestus1", 6.47], ["aeneas", 5.2], ["marcus1", 4.98], ["mater", 4.73], ["pater", 4.1], ["uotum", 4.08], ["iustus", 3.68], ["tus", 3.68], ["impius", 3.41], ["parens", 3.1], ["pius", 3.1], ["uates", 3.06], ["sae", 2.98], ["antoninus", 2.95], ["cura", 2.8], ["antonini", 2.77], ["turba", 2.72], ["metellus", 2.51], ["sancio", 2.42], ["nascor", 2.4], ["q", 2.39], ["frater", 2.36], ["sacer", 2.34], ["prex", 2.32], ["scelero", 2.32], ["fortis", 2.29], ["soror", 2.26], ["tam", 2.22], ["augustus", 2.19], ["seruo", 2.19], ["cor", 2.18], ["antoninum", 2.18], ["diuus", 2.17], ["gratus", 2.16], ["officium", 2.16], ["adopto", 2.13], ["filia", 2.06], ["manes", 2.05], ["numen", 2.03], ["munus", 2.01], ["nepos", 1.99], ["felix", 1.98], ["gener", 1.98], ["mereo", 1.96], ["metello", 1.93], ["fleo", 1.91], ["amoenus", 1.9], ["os", 1.82], ["coniunx", 1.81]], "w8": [["cestus1", 6.46], ["aeneas", 5.17], ["marcus1", 5.15], ["mater", 4.56], ["uotum", 4.14], ["pater", 3.83], ["tus", 3.64], ["pius", 3.61], ["iustus", 3.58], ["impius", 3.52], ["uates", 3.16], ["parens", 3.12], ["sae", 2.98], ["antoninus", 2.94], ["antonini", 2.93], ["turba", 2.62], ["cura", 2.59], ["officium", 2.57], ["metellus", 2.48], ["nascor", 2.33], ["frater", 2.31], ["sancio", 2.3], ["q", 2.29], ["scelero", 2.29], ["prex", 2.25], ["sacer", 2.19], ["mereo", 2.17], ["hadrianus", 2.17], ["antoninum", 2.16], ["soror", 2.14], ["felix", 2.11], ["fortis", 2.1], ["adopto", 2.1], ["augustus", 2.09], ["cor", 2.08], ["diuus", 2.07], ["munus", 2.06], ["gratus", 2.01], ["manes", 2.01], ["seruo", 2.01], ["tam", 1.98], ["filia", 1.93], ["nepos", 1.93], ["filius", 1.92], ["coniunx", 1.92], ["metello", 1.91], ["narratio", 1.9], ["titus", 1.9], ["numen", 1.89], ["pietas", 1.88], ["seuerus1", 1.88], ["gener", 1.87], ["amoenus", 1.87], ["imperator", 1.83], ["pudicus", 1.82], ["amor", 1.81]], "r1": {}, "r2": [["cestus1", 6.48], ["aeneas", 5.16], ["tus", 3.52], ["uotum", 3.32], ["sae", 2.99], ["antoninus", 2.8], ["cura", 2.71], ["turba", 2.63], ["tam", 2.47], ["marcus1", 2.34], ["mater", 2.24], ["iustus", 2.13], ["munus", 2.06], ["fleo", 2.01]], "r3": [["aeneas", 7.23], ["cestus1", 6.47], ["uotum", 4.93], ["marcus1", 4.79], ["tus", 4.78], ["sae", 4.23], ["cura", 4.11], ["mater", 4.02], ["antoninus", 3.97], ["tam", 3.62], ["iustus", 3.48], ["turba", 3.47], ["nascor", 3.32], ["metellus", 3.23], ["pater", 3.14], ["sacer", 3.03], ["uates", 2.96], ["munus", 2.96], ["frater", 2.92], ["antoninum", 2.79], ["filia", 2.77], ["numen", 2.61], ["scelero", 2.54], ["fleo", 2.51], ["imperator", 2.51], ["diuus", 2.48], ["princi", 2.44], ["antonino", 2.42], ["hadrianus", 2.4], ["metello", 2.4], ["antonini", 2.39], ["manes", 2.33], ["gratus", 2.31], ["os", 2.3], ["gener", 2.28], ["parens", 2.26], ["poeta", 2.18], ["adopto", 2.15], ["sancio", 2.1], ["appello", 2.02], ["iuuenis", 2.01], ["maestus", 2.01]], "r4": [["aeneas", 7.28], ["marcus1", 6.51], ["cestus1", 6.47], ["sae", 5.18], ["tus", 5.04], ["uotum", 4.97], ["mater", 4.97], ["iustus", 4.87], ["antoninus", 4.75], ["pater", 4.7], ["tam", 4.27], ["nascor", 4.03], ["metellus", 4.01], ["cura", 3.98], ["frater", 3.86], ["turba", 3.52], ["scelero", 3.5], ["sacer", 3.48], ["antoninum", 3.41], ["uates", 3.37], ["imperator", 3.34], ["parens", 3.28], ["filia", 3.25], ["antonini", 3.24], ["munus", 3.09], ["diuus", 3.06], ["manes", 3.04], ["numen", 3.01], ["princi", 2.99], ["antonino", 2.96], ["hadrianus", 2.94], ["prex", 2.86], ["gratus", 2.85], ["mereo", 2.79], ["impius", 2.78], ["os", 2.76], ["adopto", 2.72], ["gener", 2.71], ["felix", 2.64], ["fleo", 2.59], ["seruo", 2.58], ["metello", 2.58], ["do", 2.51], ["coniunx", 2.5], ["poeta", 2.48], ["nomen", 2.47], ["placidus", 2.47], ["cognomen", 2.43], ["iuuenis", 2.42], ["appello", 2.42], ["fuluius", 2.41], ["maestus", 2.39], ["cor", 2.35], ["cogito", 2.33], ["fortis", 2.31], ["soror", 2.3], ["sancio", 2.29], ["q", 2.25], ["que", 2.25], ["scipio1", 2.25], ["somnio", 2.25], ["princeps", 2.24], ["decet", 2.24], ["lacero", 2.23], ["patria", 2.23], ["colo1", 2.21], ["flamma", 2.2], ["uictoria", 2.18], ["cito", 2.17], ["filius", 2.17], ["unicus", 2.16], ["maternus1", 2.15], ["titus", 2.14], ["ualuit", 2.13], ["celebro", 2.1], ["manus", 2.09], ["cano", 2.08], ["augustus", 2.06], ["cognomino", 2.05], ["egregius", 2.05], ["tracto", 2.04], ["inscribo", 2.03]], "r6": [["marcus1", 9.29], ["iustus", 6.61], ["pater", 6.61], ["cestus1", 6.47], ["sae", 6.46], ["aeneas", 6.33], ["mater", 5.89], ["antoninus", 5.6], ["metellus", 4.96], ["antonini", 4.92], ["tus", 4.77], ["uotum", 4.73], ["antoninum", 4.4], ["imperator", 4.28], ["filia", 4.21], ["adopto", 4.01], ["gratus", 3.93], ["impius", 3.9], ["tam", 3.87], ["parens", 3.86], ["frater", 3.83], ["antonino", 3.82], ["nomen", 3.81], ["diuus", 3.8], ["hadrianus", 3.79], ["cura", 3.78], ["felix", 3.68], ["sacer", 3.66], ["princeps", 3.63], ["mereo", 3.54], ["appello", 3.52], ["uates", 3.51], ["fortis", 3.51], ["q", 3.48], ["princi", 3.45], ["prex", 3.41], ["cognomen", 3.36], ["cogito", 3.34], ["gener", 3.34], ["turba", 3.3], ["numen", 3.22], ["maritus", 3.19], ["sancio", 3.19], ["scelero", 3.16], ["filius", 3.13], ["fuluius", 3.12], ["metello", 3.07], ["titus", 3.05], ["poeta", 3.03], ["pietas", 2.97], ["hadriani", 2.94], ["scipio1", 2.93], ["maternus1", 2.92], ["decet", 2.9], ["recipio", 2.88], ["manus", 2.86], ["munus", 2.84], ["prudens", 2.82], ["diligo", 2.79], ["nascor", 2.77], ["manes", 2.71], ["egregius", 2.69], ["colo1", 2.68], ["affinis", 2.66], ["f", 2.64], ["olym", 2.64], ["uictoria", 2.63], ["uespasianum", 2.63], ["placidus", 2.62], ["ueneror", 2.62], ["parum", 2.6], ["uxor", 2.57], ["umbra", 2.57], ["nepos", 2.56], ["seruo", 2.55], ["que", 2.53], ["sollicitudo", 2.53], ["bellum", 2.51], ["ualuit", 2.51], ["soror", 2.5], ["tracto", 2.46], ["uersiculus", 2.42], ["magnificus", 2.41], ["cognomino", 2.39], ["cor", 2.38], ["doleo", 2.35], ["designo", 2.35], ["requies", 2.34], ["profanus", 2.33], ["fidus1", 2.33], ["consul", 2.32], ["nemo", 2.31], ["cerno", 2.31], ["amoenus", 2.31], ["abeo", 2.3], ["iuuenis", 2.29], ["cito", 2.28], ["os", 2.27], ["castus1", 2.26], ["pectus", 2.25], ["serenus1", 2.25], ["unicus", 2.24], ["gratiane", 2.22], ["thebana", 2.22], ["uol", 2.22], ["traianum", 2.21], ["uul", 2.21], ["grates", 2.2], ["castus", 2.2], ["consanguineus", 2.2], ["patruus", 2.2], ["specialis", 2.19], ["precatio", 2.18], ["mullus", 2.18], ["calcaris", 2.17], ["dubius", 2.17], ["maestus", 2.17], ["lacero", 2.17], ["enimuero", 2.16], ["sciscitor", 2.16], ["cognomentum", 2.16], ["liuidus", 2.15], ["idcirco", 2.15], ["inscribo", 2.15], ["socer", 2.15], ["propinquitas", 2.14], ["en", 2.13], ["abstraho", 2.13], ["supplex", 2.12], ["caerimonia", 2.12], ["sub", 2.11], ["religiosus", 2.11], ["faueo", 2.11], ["lenitas", 2.11], ["templum", 2.1], ["tractaris", 2.1], ["ignis", 2.09], ["metelli", 2.09], ["adoptio", 2.08], ["fleo", 2.08], ["nuncupo", 2.06], ["simplicitas", 2.06], ["colo", 2.06], ["co", 2.04], ["gero1", 2.02], ["sanctus", 2.02], ["uulnus", 2.0], ["habitus", 2.0]], "r8": [["marcus1", 11.5], ["pater", 8.36], ["iustus", 7.73], ["sae", 6.98], ["cestus1", 6.47], ["antoninus", 6.25], ["antonini", 5.99], ["mater", 5.81], ["metellus", 5.66], ["aeneas", 5.39], ["antoninum", 5.21], ["adopto", 5.07], ["impius", 4.86], ["filia", 4.8], ["felix", 4.79], ["imperator", 4.74], ["gratus", 4.67], ["hadrianus", 4.6], ["aethio", 4.58], ["fortis", 4.49], ["diuus", 4.39], ["frater", 4.38], ["q", 4.38], ["antonino", 4.29], ["princeps", 4.29], ["cogito", 4.12], ["sancio", 4.11], ["uotum", 3.99], ["filius", 3.98], ["maritus", 3.9], ["parens", 3.89], ["cognomen", 3.82], ["hadriani", 3.81], ["appello", 3.8], ["tam", 3.79], ["tus", 3.77], ["pietas", 3.75], ["princi", 3.72], ["fuluius", 3.7], ["mereo", 3.66], ["uxor", 3.62], ["titus", 3.61], ["f", 3.55], ["recipio", 3.52], ["maternus1", 3.51], ["poeta", 3.48], ["decet", 3.44], ["prudens", 3.43], ["sacer", 3.39], ["metello", 3.35], ["prex", 3.31], ["uespasianum", 3.3], ["affinis", 3.27], ["scipio1", 3.18], ["seruo", 3.16], ["sollicitudo", 3.13], ["colo1", 3.06], ["magnificus", 3.05], ["turba", 3.05], ["manus", 3.05], ["uates", 3.01], ["diligo", 2.99], ["designo", 2.99], ["consul", 2.99], ["castus1", 2.99], ["uersiculus", 2.97], ["bellum", 2.92], ["sciscitor", 2.92], ["parum", 2.88], ["egregius", 2.87], ["horto", 2.87], ["profanus", 2.87], ["augustus", 2.86], ["uictoria", 2.85], ["nepos", 2.83], ["antoninos", 2.8], ["numen", 2.79], ["umbra", 2.77], ["abeo", 2.76], ["ueneror", 2.74], ["doleo", 2.73], ["indulgeo", 2.72], ["quaestor", 2.7], ["templum", 2.7], ["nemo", 2.69], ["cognomino", 2.68], ["gener", 2.67], ["amoenus", 2.67], ["dubius", 2.66], ["tracto", 2.64], ["afficio", 2.64], ["nuncupo", 2.63], ["olym", 2.63], ["thebana", 2.63], ["uol", 2.63], ["religiosus", 2.62], ["traianum", 2.61], ["castus", 2.6], ["patruus", 2.6], ["cerno", 2.6], ["specialis", 2.59], ["precatio", 2.59], ["cito", 2.59], ["mullus", 2.58], ["calcaris", 2.57], ["amo", 2.57], ["enimuero", 2.56], ["liuidus", 2.55], ["cognomentum", 2.55], ["exsequiae", 2.54], ["placidus", 2.54], ["propinquitas", 2.54], ["habitus", 2.53], ["crudelis", 2.52], ["sub", 2.51], ["uerum", 2.5], ["caerimonia", 2.5], ["lacero", 2.5], ["matrimonium", 2.5], ["lenitas", 2.49], ["idcirco", 2.49], ["lego2", 2.48], ["tractaris", 2.48], ["en", 2.48], ["transeo", 2.47], ["metelli", 2.47], ["ualuit", 2.47], ["inscribo", 2.46], ["adoptio", 2.46], ["colo", 2.46], ["simplicitas", 2.44], ["nutricius", 2.44], ["gratiane", 2.44], ["adoptatio", 2.43], ["subagrestis", 2.43], ["co", 2.42], ["adoptiuus", 2.42], ["domitianum", 2.42], ["iupiter", 2.42], ["faustinam", 2.42], ["immolaris", 2.41], ["a-rabo1", 2.4], ["consanguineus", 2.4], ["blandimentum", 2.4], ["sanctus", 2.39], ["serenus1", 2.39], ["munus", 2.38], ["abstergeo", 2.38], ["traiano", 2.38], ["nam", 2.38], ["facies", 2.37], ["beneuolus", 2.37], ["seuerus1", 2.37], ["anteeo", 2.37], ["erogo", 2.37], ["antoninorum", 2.36], ["caecilius", 2.34], ["ordino", 2.34], ["immo", 2.34], ["insons", 2.34], ["pullus", 2.33], ["requies", 2.33], ["splendidus", 2.32], ["contumax", 2.32], ["ignarus", 2.32], ["euentum", 2.32], ["soror", 2.32], ["abstraho", 2.32], ["uulnus", 2.32], ["ueneno", 2.31], ["suscipio", 2.31], ["amor", 2.31], ["anxius", 2.31], ["fidus1", 2.3], ["nolo", 2.3], ["socer", 2.29], ["defungor", 2.29], ["funero", 2.28], ["principatus", 2.27], ["extorqueo", 2.26], ["que", 2.25], ["supplex", 2.25], ["simulatio", 2.24], ["faueo", 2.24], ["seruitus", 2.23], ["cura", 2.23], ["defectio", 2.22], ["delphinum", 2.22], ["saltem", 2.22], ["platonica", 2.22], ["elephantinus", 2.22], ["troianum", 2.22], ["caueo", 2.21], ["cor", 2.21], ["reddo", 2.21], ["cunctus", 2.2], ["grates", 2.2], ["contingo", 2.2], ["uul", 2.2], ["affectus", 2.2]], "r12": [["marcus1", 14.48], ["iustus", 9.8], ["antonini", 7.56], ["sae", 7.39], ["adopto", 6.84], ["antoninus", 6.65], ["felix", 6.59], ["cestus1", 6.46], ["mater", 6.37], ["antoninum", 6.36], ["hadrianus", 6.36], ["impius", 6.35], ["metellus", 5.98], ["q", 5.64], ["gratus", 5.59], ["imperator", 5.55], ["diuus", 5.53], ["aethio", 5.47], ["filia", 5.31], ["antonino", 5.19], ["aeneas", 5.15], ["hadriani", 5.11], ["parens", 4.95], ["frater", 4.94], ["cogito", 4.93], ["sancio", 4.86], ["maritus", 4.78], ["fortis", 4.75], ["fuluius", 4.74], ["uxor", 4.74], ["seuerus1", 4.69], ["indulgeo", 4.66], ["princeps", 4.62], ["cognomen", 4.6], ["appello", 4.59], ["mereo", 4.51], ["recipio", 4.49], ["horto", 4.48], ["antoninos", 4.44], ["seruo", 4.37], ["poeta", 4.35], ["maternus1", 4.34], ["quaestor", 4.3], ["amor", 4.29], ["pietas", 4.29], ["titus", 4.29], ["uotum", 4.28], ["affinis", 4.22], ["castus1", 4.16], ["denique", 4.1], ["sciscitor", 4.02], ["designo", 3.96], ["nolo", 3.94], ["auus", 3.92], ["augustus", 3.91], ["afficio", 3.86], ["princi", 3.85], ["sollicitudo", 3.8], ["hispania", 3.79], ["metello", 3.71], ["magnificus", 3.65], ["antoninorum", 3.64], ["decet", 3.64], ["prudens", 3.63], ["caecilius", 3.62], ["colo1", 3.61], ["diligo", 3.6], ["diuinus", 3.59], ["transeo", 3.58], ["uersiculus", 3.57], ["sacer", 3.56], ["templum", 3.51], ["prex", 3.5], ["dea", 3.5], ["uates", 3.48], ["consul", 3.46], ["adoptatio", 3.45], ["uulnus", 3.44], ["tus", 3.43], ["uespasianum", 3.43], ["f", 3.42], ["abeo", 3.41], ["patruus", 3.41], ["amo", 3.38], ["macer", 3.33], ["dubius", 3.33], ["lego2", 3.32], ["scilicet", 3.32], ["nepos", 3.3], ["profanus", 3.27], ["ueneror", 3.25], ["specialis", 3.24], ["aper", 3.24], ["adipe", 3.24], ["simplicitas", 3.21], ["enimuero", 3.2], ["nuncupo", 3.19], ["liuidus", 3.18], ["exsequiae", 3.18], ["lacero", 3.18], ["propinquitas", 3.18], ["cognomentum", 3.18], ["cano", 3.17], ["sub", 3.16], ["egregius", 3.16], ["cognomino", 3.16], ["ueneno", 3.15], ["ahenobarbus", 3.14], ["commodus1", 3.14], ["optume", 3.13], ["idcirco", 3.13], ["adoptiuus", 3.13], ["subagrestis", 3.13], ["faustinam", 3.12], ["fugo", 3.12], ["parcus", 3.11], ["saltem", 3.11], ["nemo", 3.11], ["a-rabo1", 3.1], ["turba", 3.1], ["inde", 3.09], ["umbra", 3.08], ["metelli", 3.08], ["cito", 3.07], ["adoptio", 3.07], ["numen", 3.07], ["colo", 3.07], ["mullus", 3.07], ["traiano", 3.06], ["erogo", 3.06], ["calcaris", 3.05], ["condicio", 3.04], ["defungor", 3.03], ["pullus", 3.02], ["scipio1", 3.02], ["contio", 3.02], ["contumax", 3.01], ["officium", 3.0], ["placidus", 2.99], ["euentum", 2.99], ["sanctus", 2.99], ["uol", 2.98], ["timeo", 2.98], ["inscribo", 2.97], ["elephantinus", 2.97], ["participo", 2.97], ["rapio", 2.96], ["funero", 2.96], ["affectus", 2.95], ["faustina", 2.95], ["perenno", 2.95], ["persecutor", 2.95], ["castus", 2.94], ["olla", 2.94], ["imito", 2.93], ["extorqueo", 2.92], ["precatio", 2.92], ["uerum", 2.91], ["mortalia", 2.91], ["ordino", 2.91], ["magnitude", 2.9], ["necessarius", 2.9], ["traianus", 2.89], ["cunctus", 2.89], ["munus", 2.88], ["ignarus", 2.87], ["defectio", 2.87], ["anxius", 2.87], ["insinuo", 2.84], ["fingo", 2.84], ["arcanus1", 2.84], ["principatus", 2.84], ["contexo", 2.83], ["seuerus", 2.82], ["paternus", 2.82], ["podagra", 2.82], ["nutricius", 2.81], ["locupletissimum", 2.81], ["arrium", 2.81], ["platonica", 2.81], ["ueneraris", 2.81], ["crudelis", 2.81], ["supplex", 2.8], ["humaniter", 2.8], ["faueo", 2.79], ["seruitus", 2.79], ["remaneo", 2.79], ["caerimonia", 2.79], ["amita", 2.78], ["proconsulis", 2.77], ["lenitas", 2.77], ["cuniculus", 2.77], ["liberalitas", 2.76], ["cognatus", 2.74], ["asperitas", 2.74], ["reddo", 2.72], ["suscipio", 2.71], ["posteritas", 2.71], ["complexus", 2.71], ["consecro", 2.7]], "r16": [["marcus1", 16.38], ["iustus", 11.24], ["antonini", 8.8], ["adopto", 8.13], ["felix", 8.0], ["hadrianus", 7.47], ["impius", 7.36], ["antoninum", 7.27], ["sae", 7.03], ["antoninus", 6.89], ["hadriani", 6.46], ["cestus1", 6.46], ["mater", 6.42], ["antonino", 6.21], ["metellus", 6.15], ["gratus", 6.07], ["seuerus1", 6.06], ["imperator", 6.05], ["indulgeo", 5.96], ["diuus", 5.95], ["pietas", 5.66], ["seruo", 5.64], ["sancio", 5.58], ["parens", 5.54], ["amor", 5.53], ["q", 5.53], ["aethio", 5.46], ["horto", 5.39], ["denique", 5.38], ["quaestor", 5.38], ["antoninos", 5.34], ["filia", 5.33], ["recipio", 5.22], ["cognomen", 5.19], ["maritus", 5.19], ["princeps", 5.15], ["aeneas", 5.12], ["auus", 5.1], ["nolo", 5.07], ["fortis", 5.05], ["fuluius", 5.03], ["affinis", 5.01], ["poeta", 5.0], ["titus", 4.98], ["uotum", 4.97], ["designo", 4.97], ["uxor", 4.94], ["mereo", 4.93], ["antoninorum", 4.9], ["sciscitor", 4.88], ["cogito", 4.78], ["diuinus", 4.76], ["maternus1", 4.74], ["afficio", 4.66], ["frater", 4.62], ["dea", 4.55], ["castus1", 4.55], ["nepos", 4.46], ["sub", 4.39], ["uates", 4.37], ["commodus1", 4.29], ["cognomentum", 4.21], ["sollicitudo", 4.17], ["diligo", 4.1], ["prex", 4.1], ["princi", 4.09], ["magnificus", 4.07], ["optume", 4.02], ["templum", 4.01], ["adoptatio", 3.98], ["cano", 3.97], ["scilicet", 3.97], ["uulnus", 3.95], ["colo1", 3.95], ["patruus", 3.93], ["gladiatorius", 3.92], ["fingo", 3.9], ["cognomino", 3.89], ["asperitas", 3.88], ["transeo", 3.88], ["prudens", 3.87], ["parcus", 3.87], ["macer", 3.85], ["error", 3.85], ["uersiculus", 3.83], ["remaneo", 3.82], ["iniustus", 3.79], ["augustus", 3.79], ["impietas", 3.78], ["necessarius", 3.76], ["fugo", 3.75], ["consul", 3.74], ["aper", 3.74], ["abeo", 3.73], ["ahenobarbus", 3.72], ["exsequiae", 3.71], ["liuidus", 3.71], ["posteritas", 3.71], ["ueneror", 3.71], ["adoptiuus", 3.7], ["faustinam", 3.7], ["subagrestis", 3.7], ["nuncupo", 3.67], ["rapio", 3.66], ["participo", 3.65], ["sulla", 3.65], ["lacero", 3.63], ["traiano", 3.62], ["amo", 3.61], ["adoptio", 3.61], ["memoro", 3.58], ["contumax", 3.58], ["caecilius", 3.58], ["elephantinus", 3.57], ["uersus", 3.57], ["tus", 3.56], ["euentum", 3.55], ["perenno", 3.55], ["persecutor", 3.55], ["sacer", 3.53], ["funero", 3.53], ["defungor", 3.52], ["imperium", 3.5], ["dubius", 3.5], ["sanctus", 3.49], ["traianus", 3.48], ["tormentum", 3.47], ["extorqueo", 3.47], ["accuso", 3.47], ["inscribo", 3.47], ["decet", 3.47], ["successor", 3.45], ["pullus", 3.45], ["inde", 3.45], ["locupletissimum", 3.44], ["ueneraris", 3.44], ["ciuis", 3.43], ["contio", 3.43], ["humaniter", 3.43], ["placidus", 3.43], ["contexo", 3.42], ["affectus", 3.42], ["insinuo", 3.42], ["defectio", 3.42], ["uespasianum", 3.41], ["umbra", 3.41], ["amita", 3.41], ["munus", 3.4], ["cuniculus", 3.4], ["seuerus", 3.4], ["ordino", 3.4], ["aura", 3.39], ["imito", 3.38], ["profanus", 3.38], ["centum", 3.37], ["arcanus1", 3.37], ["anxius", 3.36], ["iussus", 3.35], ["principatus", 3.35], ["erogo", 3.35], ["proconsulis", 3.34], ["scelus", 3.34], ["officium", 3.34], ["f", 3.33], ["utpote", 3.32], ["adipe", 3.32], ["hispania", 3.32], ["libro", 3.31], ["enimuero", 3.31], ["celsus1", 3.3], ["theodosio", 3.3], ["arrium", 3.3], ["seruitus", 3.3], ["ophiusa1", 3.29], ["mamaeae", 3.29], ["impudicitia", 3.29], ["supplex", 3.28], ["helio", 3.28], ["amabilis", 3.28], ["nerua", 3.28], ["homerus", 3.28], ["aurelio", 3.27], ["examen", 3.26], ["paternus", 3.26], ["ueneno", 3.25], ["sallustium", 3.25], ["cito", 3.23], ["praenomen", 3.23], ["nemo", 3.22], ["geta", 3.22], ["specialis", 3.22], ["agito", 3.21], ["uespasianus", 3.21], ["consecro", 3.21], ["satis", 3.2], ["sortio", 3.19], ["reddo", 3.19], ["pudicus", 3.18], ["paeniteo", 3.18], ["insanio", 3.18]]}