{"w1": {}, "w2": {}, "w3": {}, "w4": {}, "w6": [["panis", 2.0]], "w8": [["panis", 1.99]], "r1": {}, "r2": {}, "r3": {}, "r4": [["cibo", 2.45]], "r6": [["cibo", 3.16], ["panis", 2.99], ["caelestis", 2.43], ["esus2", 2.24], ["eremus", 2.23], ["solummodo", 2.23], ["lego", 2.21], ["lateo", 2.2]], "r8": [["panis", 4.11], ["cibo", 3.74], ["caelestis", 3.14], ["angelus", 2.81], ["nunc", 2.81], ["esus2", 2.64], ["eremus", 2.64], ["solummodo", 2.64], ["lego", 2.61], ["lateo", 2.6], ["xl", 2.44], ["calculus", 2.44], ["biduus", 2.44], ["permitto", 2.41], ["lego2", 2.4], ["sero1", 2.39], ["caro", 2.39], ["caelum", 2.35], ["populus", 2.23], ["quinque", 2.21], ["piscis", 2.21], ["candidus", 2.21], ["desidero", 2.19], ["beneficium", 2.19], ["secundus", 2.12], ["annus", 2.06], ["quisque", 2.01]], "r12": [["panis", 5.37], ["cibo", 4.69], ["angelus", 3.98], ["caelestis", 3.97], ["pasco", 3.44], ["piscis", 3.43], ["esus2", 3.32], ["eremus", 3.31], ["lateo", 3.26], ["xl", 3.15], ["calculus", 3.15], ["lego2", 3.1], ["sero1", 3.08], ["candidus", 2.96], ["annus", 2.94], ["beneficium", 2.94], ["secundus", 2.85], ["solummodo", 2.82], ["emitto", 2.79], ["desidero", 2.77], ["permitto", 2.77], ["caro", 2.73], ["transueho", 2.64], ["dominus", 2.64], ["obligo", 2.64], ["instar", 2.63], ["quinque", 2.61], ["lego", 2.58], ["cibus", 2.5], ["sabbatum", 2.44], ["pelagus", 2.44], ["aeternitas", 2.44], ["circiter", 2.43], ["biduus", 2.43], ["mors", 2.42], ["ignosco", 2.4], ["quando", 2.36], ["materia", 2.34], ["caelum", 2.27], ["erythraeus", 2.23], ["serpens", 2.21], ["redigo", 2.2], ["saeculis", 2.2], ["inferus", 2.18], ["edo1", 2.16]], "r16": [["panis", 6.3], ["cibo", 5.48], ["angelus", 4.87], ["pasco", 4.45], ["caelestis", 4.43], ["esus2", 3.87], ["eremus", 3.87], ["piscis", 3.84], ["xl", 3.73], ["calculus", 3.73], ["lego2", 3.66], ["sero1", 3.65], ["candidus", 3.57], ["beneficium", 3.54], ["lateo", 3.52], ["contamino", 3.46], ["aeternitas", 3.45], ["instar", 3.45], ["passio", 3.45], ["redigo", 3.43], ["saeculis", 3.43], ["cibus", 3.32], ["transueho", 3.31], ["obligo", 3.31], ["humanus", 3.3], ["pelagus", 3.15], ["secundus", 3.12], ["ignosco", 3.11], ["dominus", 3.1], ["quando", 3.06], ["materia", 3.04], ["erythraeus", 3.0], ["inferus", 2.94], ["edo1", 2.92], ["ferreus", 2.81], ["mors", 2.72], ["uirga", 2.62], ["quinque", 2.59], ["solummodo", 2.44], ["sabbatum", 2.44], ["quadraginta", 2.43], ["circiter", 2.43], ["biduus", 2.43], ["serpens", 2.42], ["terrenus", 2.41], ["obliuiscor", 2.4], ["ferio", 2.4], ["emitto", 2.38], ["desidero", 2.35], ["permitto", 2.35], ["lego", 2.35], ["arbor", 2.33], ["caro", 2.29], ["pridianus", 2.23], ["exalto", 2.23], ["infringo", 2.22], ["potestas", 2.2], ["caelum", 2.19], ["sequor", 2.12]]}