{"w1": {}, "w2": [["et", 1.88]], "w3": {}, "w4": {}, "w6": {}, "w8": {}, "r1": {}, "r2": {}, "r3": {}, "r4": {}, "r6": [["nomen", 2.45], ["ceraris", 2.24], ["obseruatio", 2.23], ["qualitas", 2.23], ["inscribo", 2.23], ["signo", 2.22], ["sufficio", 2.22], ["attingo", 2.22], ["fructus", 2.22], ["aedes", 2.2], ["templum", 2.19], ["tunc", 2.16], ["at", 2.15], ["consilium", 2.11]], "r8": [["templum", 2.95], ["ceraris", 2.65], ["qualitas", 2.63], ["inscribo", 2.63], ["signo", 2.63], ["sufficio", 2.62], ["fructus", 2.62], ["aedes", 2.6], ["tunc", 2.55], ["at", 2.54], ["pro-eo1", 2.44], ["obseruatio", 2.44], ["inanis", 2.42], ["pingo", 2.41], ["tenuis", 2.4], ["immo", 2.4], ["ostendo", 2.34], ["pabulor", 2.24], ["macra", 2.23], ["pigeo", 2.23], ["ualles", 2.22], ["amicus1", 2.22], ["attingo", 2.2], ["tabula", 2.19], ["sicut", 2.09], ["uiuo", 2.09], ["consilium", 2.03], ["urbs", 2.0]], "r12": [["templum", 3.66], ["ceraris", 3.32], ["qualitas", 3.3], ["inscribo", 3.3], ["signo", 3.3], ["sufficio", 3.28], ["fructus", 3.28], ["tunc", 3.18], ["at", 3.17], ["inanis", 3.12], ["pingo", 3.11], ["tenuis", 3.1], ["immo", 3.09], ["ostendo", 3.0], ["pabulor", 3.0], ["macra", 3.0], ["pro-eo1", 2.99], ["amicus1", 2.97], ["testamentum", 2.96], ["tabula", 2.94], ["apis", 2.81], ["iugum", 2.78], ["aedes", 2.75], ["urbs", 2.68], ["fauus", 2.64], ["luxurio", 2.64], ["cera", 2.63], ["sicut", 2.62], ["teneo", 2.59], ["signum", 2.48], ["uitium", 2.48], ["denotaris", 2.45], ["paucitas", 2.44], ["hodiernus", 2.44], ["pigeo", 2.44], ["ualles", 2.43], ["obseruatio", 2.42], ["paulatim", 2.4], ["edo2", 2.4], ["floreo", 2.36], ["impero", 2.35], ["facilis", 2.35], ["arbor", 2.34], ["alienus", 2.26], ["spiritus", 2.24], ["aduolo", 2.23], ["serpens", 2.21], ["tener", 2.2], ["attingo", 2.18], ["omne", 2.18], ["nimius", 2.11], ["ceterus", 2.07]], "r16": [["ostendo", 4.07], ["testamentum", 3.96], ["qualitas", 3.85], ["inscribo", 3.85], ["signo", 3.85], ["sufficio", 3.83], ["fructus", 3.83], ["templum", 3.76], ["inanis", 3.69], ["tenuis", 3.66], ["immo", 3.66], ["ceraris", 3.6], ["macra", 3.6], ["amicus1", 3.58], ["tunc", 3.57], ["at", 3.41], ["iugum", 3.41], ["fauus", 3.31], ["luxurio", 3.31], ["cera", 3.3], ["apis", 3.3], ["pingo", 3.25], ["teneo", 3.19], ["paucitas", 3.15], ["tabula", 3.08], ["arbor", 3.04], ["pabulor", 3.0], ["aduolo", 2.99], ["pro-eo1", 2.99], ["tener", 2.96], ["alienus", 2.95], ["edo2", 2.94], ["omne", 2.94], ["spiritus", 2.93], ["nimius", 2.87], ["corporaliter", 2.83], ["uitium", 2.8], ["pinguis", 2.78], ["scriptor", 2.78], ["paulatim", 2.77], ["reliquus", 2.74], ["italia", 2.67], ["lucidus", 2.64], ["signum", 2.61], ["serpens", 2.61], ["colligo1", 2.56], ["floreo", 2.53], ["legatus", 2.46], ["denotaris", 2.45], ["anima", 2.44], ["pigeo", 2.44], ["uanitas", 2.43], ["exprobro", 2.43], ["ualles", 2.42], ["obseruatio", 2.41], ["corrumpo", 2.37], ["caueo", 2.31], ["impero", 2.3], ["ascribo", 2.23], ["obsigno", 2.22], ["mereo", 2.22], ["dedecor", 2.22], ["laeto", 2.19], ["sublimis", 2.18], ["donum", 2.17], ["attingo", 2.15], ["mel", 2.06], ["plenus", 2.04]]}