{"w1": [["y", 3.0]], "w2": [["y", 3.0]], "w3": [["y", 3.0]], "w4": [["y", 3.0]], "w6": [["y", 3.0], ["e", 1.85]], "w8": [["y", 3.0], ["e", 1.82]], "r1": {}, "r2": [["y", 3.0]], "r3": [["y", 4.24]], "r4": [["y", 5.0], ["minum", 2.45], ["uestigium", 2.42], ["o", 2.38]], "r6": [["y", 6.08], ["minum", 3.16], ["uestigium", 3.13], ["o", 3.08], ["e", 2.46], ["eretria", 2.24], ["alpibus", 2.23], ["pinus", 2.23], ["amaritudo", 2.23], ["terminus", 2.22], ["colonia", 2.2], ["cero", 2.19]], "r8": [["y", 6.85], ["thago", 4.58], ["minum", 3.74], ["uestigium", 3.69], ["o", 3.64], ["e", 3.16], ["uoco", 2.99], ["colonia", 2.79], ["eretria", 2.64], ["alpibus", 2.64], ["pinus", 2.64], ["amaritudo", 2.63], ["terminus", 2.62], ["cero", 2.59], ["os1", 2.44], ["myrtum", 2.44], ["destringo", 2.44], ["quercus", 2.44], ["oceanus", 2.41], ["placidus", 2.41], ["uua", 2.4], ["fateor", 2.39], ["uis", 2.38], ["ardeo", 2.38], ["profecto", 2.36], ["deduco", 2.35], ["templum", 2.31], ["sto", 2.26], ["eo1", 2.25], ["aceo", 2.23], ["cxx", 2.23], ["ursus", 2.23], ["callus", 2.22], ["xi", 2.22], ["indignor", 2.21], ["usque", 2.19], ["columna", 2.19], ["serpo", 2.17], ["soror", 2.14], ["sucus", 2.13], ["procedo", 2.12], ["lego", 2.12], ["folium", 2.05], ["radix", 2.04]], "r12": [["y", 7.92], ["thago", 5.66], ["uestigium", 4.62], ["o", 4.56], ["minum", 4.24], ["myrtum", 3.73], ["colonia", 3.4], ["uoco", 3.38], ["eretria", 3.32], ["alpibus", 3.31], ["amaritudo", 3.3], ["terminus", 3.28], ["cero", 3.24], ["sucus", 3.19], ["prodo", 3.18], ["geraesto", 3.16], ["pinus", 3.15], ["destringo", 3.14], ["oceanus", 3.11], ["placidus", 3.1], ["uua", 3.1], ["ardeo", 3.06], ["deduco", 3.01], ["aceo", 2.99], ["cxx", 2.99], ["ursus", 2.99], ["os1", 2.99], ["quercus", 2.98], ["callus", 2.98], ["indignor", 2.97], ["sto", 2.91], ["profecto", 2.87], ["procedo", 2.84], ["lego", 2.84], ["praeligo", 2.82], ["tilia", 2.82], ["pirum", 2.82], ["aulis", 2.82], ["brassica", 2.82], ["uiolens", 2.81], ["xi", 2.81], ["usque", 2.8], ["carthago", 2.78], ["templum", 2.78], ["columna", 2.76], ["radix", 2.75], ["interuallum", 2.74], ["exiguus", 2.71], ["probo", 2.68], ["pes", 2.65], ["opulus", 2.64], ["larice", 2.64], ["crusta", 2.63], ["carpo", 2.61], ["folium", 2.58], ["latitudo", 2.56], ["acuo", 2.56], ["discrimen", 2.56], ["fateor", 2.54], ["diligens", 2.54], ["ibi", 2.54], ["m", 2.51], ["eo1", 2.51], ["propter", 2.5], ["oppidum", 2.49], ["fons", 2.48], ["contrarius", 2.45], ["existimo", 2.45], ["uenetia", 2.45], ["arethusa", 2.45], ["folliculus", 2.45], ["bisulcus", 2.44], ["grauedo", 2.44], ["tantisper", 2.44], ["atheniensis", 2.43], ["circulus", 2.42], ["agrippa", 2.42], ["cornelius", 2.39], ["flumen", 2.39], ["longus", 2.39], ["ob", 2.37], ["cornu", 2.34], ["paucus", 2.3], ["magister", 2.26], ["ager", 2.26], ["mae", 2.23], ["era", 2.23], ["salix", 2.22], ["excipio", 2.21], ["pungo", 2.19], ["collegium", 2.19], ["calidus", 2.15], ["rideo", 2.14], ["placeo", 2.11], ["ignis", 2.1], ["propior", 2.09], ["soror", 2.07], ["error", 2.06], ["contineo", 2.03]], "r16": [["y", 8.35], ["thago", 5.92], ["uestigium", 5.21], ["minum", 4.24], ["myrtum", 4.23], ["o", 4.06], ["flumen", 4.03], ["colonia", 3.92], ["sucus", 3.88], ["eretria", 3.87], ["m", 3.79], ["cero", 3.79], ["geraesto", 3.74], ["alpibus", 3.73], ["placidus", 3.67], ["uua", 3.67], ["arethusa", 3.6], ["cxx", 3.59], ["callus", 3.59], ["deduco", 3.57], ["pes", 3.52], ["sto", 3.47], ["praeligo", 3.46], ["pirum", 3.46], ["aulis", 3.45], ["brassica", 3.45], ["fons", 3.45], ["procedo", 3.43], ["terminus", 3.42], ["carthago", 3.41], ["interuallum", 3.37], ["ardeo", 3.34], ["exiguus", 3.34], ["larice", 3.31], ["crusta", 3.3], ["amaritudo", 3.3], ["uiolens", 3.29], ["destringo", 3.29], ["prodo", 3.29], ["carpo", 3.28], ["indignor", 3.28], ["discrimen", 3.22], ["radix", 3.2], ["usque", 3.18], ["bisulcus", 3.16], ["folliculus", 3.16], ["tantisper", 3.15], ["ibi", 3.15], ["ursus", 3.14], ["circulus", 3.13], ["oppidum", 3.11], ["cornelius", 3.1], ["mae", 2.99], ["os1", 2.98], ["paucus", 2.95], ["probo", 2.95], ["calidus", 2.92], ["excipio", 2.92], ["rideo", 2.9], ["propter", 2.9], ["placeo", 2.83], ["error", 2.83], ["conputatio", 2.83], ["tamarix", 2.82], ["basis", 2.82], ["culleus", 2.81], ["pal", 2.81], ["ob", 2.8], ["pungo", 2.78], ["collegium", 2.78], ["columna", 2.74], ["uoluo", 2.73], ["latitudo", 2.73], ["contineo", 2.73], ["acuo", 2.72], ["serus", 2.72], ["aduerto", 2.71], ["templum", 2.7], ["mora", 2.7], ["nobilis", 2.68], ["profecto", 2.64], ["opulus", 2.64], ["tilia", 2.64], ["aceo", 2.64], ["castrum", 2.63], ["cartilago", 2.63], ["pinus", 2.62], ["quercus", 2.62], ["xi", 2.62], ["agrippa", 2.61], ["magister", 2.61], ["lego", 2.61], ["defluo", 2.6], ["fastigium", 2.58], ["oceanus", 2.56], ["metior", 2.54], ["folium", 2.54], ["carnis", 2.53], ["propono", 2.52], ["diligens", 2.51], ["fateor", 2.51], ["sicut", 2.45], ["uenetia", 2.45], ["danuuium", 2.44], ["grauedo", 2.44], ["persicum", 2.44], ["crepo", 2.43], ["atheniensis", 2.43], ["praeeo", 2.42], ["nucleus", 2.42], ["eo1", 2.4], ["contrarius", 2.39], ["commendatio", 2.38], ["paulum", 2.32], ["cornu", 2.31], ["pius", 2.3], ["dum", 2.29], ["canopum", 2.23], ["san", 2.23], ["chalcis1", 2.22], ["coniectus", 2.22], ["era", 2.22], ["salix", 2.22], ["propior", 2.21], ["saepis", 2.2], ["eruptio", 2.2], ["promunturium", 2.18], ["granum", 2.18], ["ager", 2.15], ["dius", 2.13], ["existimo", 2.11], ["pario", 2.07], ["auis", 2.04]]}