{"w1": {}, "w2": [["fax", 1.99]], "w3": [["fax", 2.23], ["cena", 1.99]], "w4": [["fax", 2.23], ["cena", 1.99]], "w6": [["fax", 2.44], ["cena", 1.98]], "w8": [["fax", 2.43], ["cena", 1.98]], "r1": {}, "r2": {}, "r3": [["fax", 2.44], ["cena", 2.44]], "r4": [["fax", 3.15], ["cena", 2.99], ["conuiuium", 2.43]], "r6": [["fax", 3.86], ["cena", 3.29], ["conuiuium", 3.13], ["nox", 3.04], ["uelut", 2.56], ["uirgo", 2.37], ["praeluceo", 2.24], ["decenter", 2.24], ["concubius", 2.23], ["rudimentum", 2.23], ["affluo", 2.23], ["uoueo", 2.23], ["taeda", 2.23], ["epulae", 2.23], ["thalamus", 2.22], ["pacisco", 2.21], ["donum", 2.2], ["egredior", 2.2], ["mando1", 2.19], ["munus", 2.14], ["mundus", 2.13], ["uinum", 2.04], ["nosco", 2.04]], "r8": [["fax", 4.46], ["nox", 3.6], ["cena", 3.28], ["conuiuium", 3.11], ["uelut", 2.88], ["praeluceo", 2.83], ["accumbo", 2.82], ["uirgo", 2.73], ["decenter", 2.64], ["concubius", 2.64], ["rudimentum", 2.64], ["uoueo", 2.64], ["taeda", 2.64], ["thalamus", 2.63], ["pacisco", 2.62], ["donum", 2.61], ["tabula", 2.57], ["munus", 2.53], ["mundus", 2.51], ["pignero", 2.45], ["iugal", 2.45], ["dotal", 2.45], ["epulae", 2.44], ["madeo", 2.44], ["offero", 2.44], ["omen", 2.42], ["tolero", 2.42], ["limen", 2.42], ["uestio", 2.41], ["desero2", 2.41], ["nosco", 2.41], ["egredior", 2.39], ["permitto", 2.36], ["peto", 2.33], ["orno", 2.32], ["cunctus", 2.31], ["lima", 2.23], ["mellitus", 2.23], ["affluo", 2.23], ["priscus", 2.22], ["flagito", 2.22], ["ibidem", 2.22], ["piso", 2.21], ["toga", 2.21], ["aetas", 2.21], ["infelix", 2.2], ["pridem", 2.2], ["congruo", 2.2], ["honor", 2.2], ["cubiculum", 2.19], ["filius", 2.19], ["exhibeo", 2.19], ["obeo", 2.19], ["uinum", 2.19], ["nuptiae", 2.18], ["uilla", 2.18], ["mando1", 2.16], ["oleum", 2.11]], "r12": [["fax", 4.88], ["nox", 4.5], ["tabula", 3.79], ["filia", 3.63], ["uirgo", 3.48], ["praeluceo", 3.46], ["cubiculum", 3.42], ["concubius", 3.31], ["rudimentum", 3.31], ["taeda", 3.31], ["uoueo", 3.31], ["thalamus", 3.3], ["pacisco", 3.28], ["munus", 3.17], ["pignero", 3.16], ["dotal", 3.16], ["iugal", 3.16], ["accumbo", 3.16], ["offero", 3.14], ["omen", 3.13], ["limen", 3.13], ["uestio", 3.11], ["desero2", 3.11], ["cena", 3.1], ["conuiuium", 3.08], ["permitto", 3.04], ["nosco", 3.01], ["decenter", 3.0], ["lima", 3.0], ["mellitus", 3.0], ["priscus", 2.98], ["ibidem", 2.97], ["cunctus", 2.97], ["pridem", 2.96], ["torus", 2.96], ["nuptiae", 2.94], ["fides", 2.91], ["denique", 2.91], ["peto", 2.89], ["superus", 2.86], ["oleum", 2.85], ["aetas", 2.84], ["honor", 2.84], ["sauiis", 2.83], ["tenuo", 2.82], ["orno", 2.82], ["uelut", 2.8], ["mutuus", 2.79], ["puella", 2.77], ["destino", 2.75], ["maritus", 2.75], ["lacrima", 2.74], ["mirus", 2.69], ["crebriter", 2.64], ["affectio", 2.63], ["gremium", 2.62], ["cubile", 2.62], ["detrimentum", 2.62], ["fors", 2.62], ["consensus", 2.62], ["mundus", 2.62], ["polio1", 2.61], ["praeparo", 2.61], ["tolero", 2.61], ["praeclaris", 2.61], ["toga", 2.6], ["congruo", 2.59], ["donum", 2.58], ["imperium", 2.57], ["salus", 2.53], ["spes", 2.51], ["statuo", 2.48], ["fragro", 2.45], ["balsamum", 2.44], ["gratulatio", 2.43], ["ex-tingo", 2.43], ["epulae", 2.43], ["madeo", 2.43], ["forma", 2.43], ["ingero", 2.42], ["conspicuus", 2.42], ["octauus", 2.42], ["rursum", 2.42], ["caritas", 2.41], ["uirilis", 2.41], ["mos", 2.4], ["cacumen", 2.4], ["infelix", 2.4], ["studiosus", 2.38], ["uilla", 2.37], ["egredior", 2.36], ["uenus", 2.33], ["confirmo", 2.32], ["lapis", 2.31], ["parens", 2.25], ["psychen", 2.23], ["moechiae", 2.23], ["affluo", 2.22], ["re-meo", 2.22], ["fabrico", 2.21], ["adoleo1", 2.21], ["flagito", 2.2], ["marito", 2.2], ["plerus", 2.2], ["ignarus", 2.19], ["piso", 2.19], ["exhibeo", 2.16], ["obeo", 2.16], ["optume", 2.15], ["requiro", 2.13], ["mando1", 2.11], ["at", 2.09], ["habitus", 2.07], ["uinum", 2.03], ["fama", 2.03], ["sancio", 2.0]], "r16": [["fax", 5.17], ["nox", 4.96], ["tabula", 4.7], ["filia", 4.23], ["cubiculum", 4.19], ["nuptiae", 4.19], ["praeluceo", 4.0], ["fides", 3.93], ["uoueo", 3.86], ["taeda", 3.86], ["uirgo", 3.85], ["pacisco", 3.83], ["dotal", 3.74], ["pignero", 3.74], ["iugal", 3.74], ["omen", 3.7], ["spes", 3.69], ["uestio", 3.68], ["desero2", 3.68], ["conuiuium", 3.64], ["concubius", 3.6], ["permitto", 3.6], ["thalamus", 3.59], ["ibidem", 3.57], ["denique", 3.57], ["pridem", 3.56], ["torus", 3.56], ["cunctus", 3.51], ["nosco", 3.51], ["rudimentum", 3.46], ["oleum", 3.44], ["mutuus", 3.42], ["limen", 3.42], ["puella", 3.39], ["destino", 3.37], ["maritus", 3.37], ["lacrima", 3.36], ["affectio", 3.3], ["priscus", 3.29], ["consensus", 3.28], ["polio1", 3.28], ["praeparo", 3.28], ["fors", 3.22], ["mons", 3.19], ["accumbo", 3.15], ["gratulatio", 3.14], ["ex-tingo", 3.14], ["offero", 3.13], ["statuo", 3.13], ["rursum", 3.12], ["caritas", 3.12], ["salus", 3.12], ["cacumen", 3.11], ["parens", 3.11], ["munus", 3.1], ["studiosus", 3.09], ["cena", 3.08], ["aetas", 3.06], ["summus", 3.04], ["sauiis", 3.0], ["decenter", 3.0], ["lima", 3.0], ["crebriter", 3.0], ["mellitus", 3.0], ["moechiae", 2.99], ["fabrico", 2.98], ["ingero", 2.97], ["cubile", 2.97], ["plerus", 2.96], ["requiro", 2.89], ["sacellum", 2.82], ["mirus", 2.82], ["tenuo", 2.82], ["abundantia", 2.8], ["adoleo1", 2.8], ["gremium", 2.8], ["at", 2.78], ["dum", 2.77], ["funus", 2.76], ["subtilis", 2.76], ["sancio", 2.75], ["orno", 2.74], ["optume", 2.73], ["deicio", 2.72], ["uelut", 2.72], ["honor", 2.71], ["confirmo", 2.67], ["paro1", 2.67], ["mos", 2.64], ["fornicatio", 2.63], ["detrimentum", 2.61], ["fama", 2.6], ["tolero", 2.59], ["praeclaris", 2.59], ["toga", 2.59], ["imperium", 2.58], ["congruo", 2.57], ["donum", 2.56], ["secundus", 2.55], ["mundus", 2.54], ["pereo", 2.53], ["habitus", 2.45], ["uulcanus", 2.45], ["domuitio", 2.45], ["relinquo", 2.45], ["fragro", 2.45], ["reuincio", 2.44], ["balsamum", 2.44], ["re-meo", 2.43], ["epulae", 2.42], ["madeo", 2.42], ["liberi", 2.41], ["nuncupo", 2.41], ["conspicuus", 2.41], ["octauus", 2.41], ["uirilis", 2.39], ["en", 2.39], ["infelix", 2.38], ["arduus", 2.38], ["disto", 2.37], ["concito", 2.36], ["uilla", 2.34], ["forma", 2.34], ["totus1", 2.34], ["paries", 2.34], ["interim", 2.32], ["egredior", 2.32], ["uenus", 2.29], ["lapis", 2.25], ["pinnulis", 2.23], ["psychen", 2.23], ["affluo", 2.21], ["natal", 2.2], ["complexus", 2.2], ["lauacrum", 2.19], ["saltus1", 2.19], ["marito", 2.19], ["flagito", 2.19], ["piso", 2.17], ["ignarus", 2.17], ["equus", 2.16], ["queo", 2.16], ["rodo", 2.14], ["exhibeo", 2.14], ["obeo", 2.13], ["uotum", 2.12], ["mando1", 2.06], ["soror", 2.05], ["premo", 2.03], ["immo", 2.01], ["diuerto", 2.01]]}