{"w1": {}, "w2": {}, "w3": {}, "w4": {}, "w6": {}, "w8": {}, "r1": {}, "r2": {}, "r3": {}, "r4": {}, "r6": [["sanus", 2.21], ["consto", 2.19], ["nascor", 2.18]], "r8": [["sanus", 2.62], ["consto", 2.59], ["marsicum", 2.45], ["aliubi", 2.45], ["efficax", 2.44], ["nascor", 2.38], ["nicander", 2.24], ["usquam", 2.23], ["medicamentum", 2.22], ["bellum", 2.11]], "r12": [["marsicum", 3.16], ["efficax", 2.99], ["consto", 2.94], ["serpo", 2.81], ["sanus", 2.79], ["optimas", 2.64], ["medicamentum", 2.63], ["aduersus", 2.61], ["nicander", 2.45], ["plaudo", 2.45], ["libero", 2.42], ["comitial", 2.23], ["asto", 2.23], ["quare", 2.22], ["h", 2.21]], "r16": {}}