{"w1": [["uolua", 2.23]], "w2": [["uolua", 2.45], ["et", 1.92]], "w3": [["uolua", 2.45], ["et", 1.91]], "w4": [["uolua", 2.83], ["oculus", 1.93], ["si", 1.92]], "w6": [["uolua", 2.82], ["oculus", 2.37], ["sedes", 2.21], ["si", 2.2], ["suffio", 2.0]], "w8": [["oculus", 2.92], ["uolua", 2.82], ["sedes", 2.2], ["si", 2.06], ["suffio", 2.0]], "r1": {}, "r2": [["uolua", 2.23]], "r3": [["uolua", 3.0], ["sedes", 2.43], ["oculus", 2.15]], "r4": [["uolua", 3.6], ["sedes", 2.97], ["oculus", 2.72], ["os", 2.53], ["suffio", 2.23], ["reprimo", 2.23], ["foueo", 2.22]], "r6": [["uolua", 4.79], ["sedes", 4.08], ["oculus", 3.59], ["os", 3.46], ["suffio", 3.16], ["reprimo", 2.99], ["foueo", 2.98], ["que", 2.77], ["pes", 2.69], ["ibi", 2.53], ["latus", 2.38], ["castoreo", 2.24], ["pusulis", 2.23], ["pupilla", 2.23], ["defatiscor", 2.23], ["inhibeo", 2.22], ["concutio", 2.22], ["iumentum", 2.22], ["bos", 2.19], ["ulcus", 2.18], ["lacrima", 2.18], ["misceo", 2.14], ["item", 2.01]], "r8": [["uolua", 5.56], ["sedes", 4.95], ["oculus", 4.61], ["os", 4.19], ["suffio", 3.99], ["reprimo", 3.59], ["que", 3.38], ["pes", 3.14], ["foueo", 2.96], ["ulcus", 2.93], ["ibi", 2.66], ["castoreo", 2.64], ["pusulis", 2.64], ["pupilla", 2.64], ["defatiscor", 2.64], ["fio", 2.63], ["inhibeo", 2.63], ["concutio", 2.63], ["iumentum", 2.62], ["bos", 2.59], ["latus", 2.55], ["carpentum", 2.44], ["relaxo", 2.44], ["uanitas", 2.43], ["alteruter", 2.43], ["sisto", 2.42], ["efficax", 2.4], ["uoluo", 2.4], ["infer", 2.39], ["stomachus", 2.39], ["repens", 2.38], ["lacrima", 2.37], ["item", 2.34], ["nam", 2.3], ["eo", 2.25], ["quapropter", 2.23], ["epiphora", 2.23], ["rimo", 2.22], ["subdo", 2.21], ["labor1", 2.2], ["umerus", 2.19], ["uua", 2.19], ["purgo", 2.18], ["mens", 2.18], ["ora", 2.17], ["oportet", 2.17], ["cutis", 2.16], ["pario", 2.16], ["uinum", 2.15], ["mare", 2.13], ["misceo", 2.08], ["femina", 2.06], ["e", 2.04]], "r12": [["oculus", 6.12], ["uolua", 5.82], ["sedes", 5.59], ["os", 4.68], ["suffio", 4.35], ["reprimo", 3.98], ["que", 3.77], ["infer", 3.69], ["pes", 3.65], ["oportet", 3.47], ["iumentum", 3.28], ["ibi", 3.27], ["carpentum", 3.15], ["femina", 3.15], ["stomachus", 3.1], ["rimo", 2.98], ["concutio", 2.98], ["subdo", 2.97], ["labor1", 2.96], ["foueo", 2.95], ["purgo", 2.95], ["uoluo", 2.94], ["potus2", 2.92], ["ulcus", 2.91], ["eo", 2.88], ["castoreo", 2.83], ["planta", 2.82], ["inhibeo", 2.8], ["tio", 2.8], ["sisto", 2.79], ["ouum", 2.78], ["remedium", 2.76], ["interdum", 2.7], ["mens", 2.68], ["uinum", 2.66], ["relaxo", 2.64], ["pilus", 2.64], ["guttur", 2.64], ["defatiscor", 2.63], ["obscenus", 2.63], ["effodio", 2.63], ["cuncto", 2.62], ["fugo", 2.61], ["muliebris", 2.6], ["minister", 2.6], ["umerus", 2.59], ["poto", 2.58], ["candidus", 2.56], ["pario", 2.55], ["repens", 2.54], ["decoquo", 2.52], ["periculum", 2.49], ["consideraris", 2.45], ["lacuna", 2.44], ["adiuuaris", 2.44], ["suspirium", 2.44], ["alo", 2.43], ["uanitas", 2.43], ["fistula", 2.41], ["arceo", 2.4], ["addo", 2.39], ["uua", 2.38], ["aridus", 2.36], ["bos", 2.36], ["lac", 2.36], ["cutis", 2.35], ["descendo", 2.35], ["lacrima", 2.34], ["tango", 2.34], ["prohibeo", 2.31], ["adduco", 2.31], ["cinis", 2.31], ["misceo", 2.25], ["latebrosus", 2.23], ["pusulis", 2.23], ["pupilla", 2.23], ["mordax", 2.23], ["quapropter", 2.22], ["epiphora", 2.22], ["pipo", 2.22], ["exter", 2.21], ["irrumpo", 2.21], ["to", 2.2], ["priuatim", 2.19], ["efficax", 2.17], ["exitium", 2.17], ["discutio", 2.17], ["ora", 2.14], ["concipio", 2.13], ["frons", 2.1], ["latus", 2.08], ["utor", 2.07]], "r16": [["oculus", 5.93], ["sedes", 5.49], ["uolua", 5.08], ["os", 5.06], ["suffio", 4.23], ["stomachus", 4.07], ["potus2", 4.06], ["pes", 4.01], ["infer", 3.95], ["iumentum", 3.84], ["oportet", 3.83], ["carpentum", 3.73], ["rimo", 3.59], ["labor1", 3.57], ["planta", 3.45], ["reprimo", 3.43], ["ouum", 3.42], ["remedium", 3.41], ["ibi", 3.39], ["cuncto", 3.29], ["candidus", 3.24], ["decoquo", 3.2], ["que", 3.18], ["lacuna", 3.16], ["fistula", 3.13], ["femina", 3.13], ["arceo", 3.12], ["aridus", 3.09], ["descendo", 3.07], ["latebrosus", 3.0], ["pilus", 2.99], ["guttur", 2.99], ["pipo", 2.98], ["concutio", 2.97], ["to", 2.97], ["subdo", 2.97], ["tio", 2.96], ["purgo", 2.94], ["foueo", 2.94], ["exitium", 2.94], ["uoluo", 2.93], ["poto", 2.93], ["addo", 2.92], ["tango", 2.89], ["adduco", 2.86], ["simul", 2.83], ["castoreo", 2.83], ["consideraris", 2.83], ["congerie", 2.82], ["cerussa", 2.82], ["effodio", 2.81], ["inhibeo", 2.8], ["purus", 2.73], ["cibus", 2.69], ["interdum", 2.67], ["pruinaris", 2.64], ["suspirium", 2.64], ["relaxo", 2.64], ["murra", 2.63], ["elicio", 2.63], ["obscenus", 2.63], ["mens", 2.62], ["uinum", 2.62], ["denarius", 2.61], ["inflammatio", 2.6], ["muliebris", 2.6], ["radix", 2.6], ["reperio", 2.58], ["umerus", 2.58], ["pario", 2.54], ["conuerto", 2.54], ["caput", 2.5], ["impetus", 2.45], ["reciproco", 2.44], ["defatiscor", 2.44], ["periculum", 2.43], ["uanitas", 2.42], ["cogo", 2.42], ["irrumpo", 2.42], ["triclinium", 2.42], ["fugo", 2.41], ["alo", 2.4], ["extraho", 2.39], ["minister", 2.39], ["uua", 2.37], ["lac", 2.34], ["cutis", 2.33], ["iugum", 2.33], ["subeo", 2.32], ["lacrima", 2.32], ["repens", 2.31], ["frons", 2.3], ["par", 2.3], ["spiritus", 2.25], ["mordax", 2.23], ["expergiscor", 2.23], ["decutio1", 2.23], ["epiphora", 2.22], ["sanies", 2.22], ["meo", 2.2], ["sisto", 2.19], ["acer", 2.18], ["uto", 2.18], ["priuatim", 2.18], ["discutio", 2.15], ["bos", 2.12], ["prohibeo", 2.06], ["cinis", 2.06], ["pondus", 2.03]]}