{"w1": {}, "w2": {}, "w3": {}, "w4": {}, "w6": {}, "w8": {}, "r1": {}, "r2": {}, "r3": {}, "r4": {}, "r6": {}, "r8": {}, "r12": [["histri", 3.32], ["urbs", 3.2], ["margo", 3.16], ["celsus1", 3.15], ["castellum", 3.15], ["ito", 3.15], ["species", 3.12], ["ctesiphontis", 3.0], ["offendo", 2.99], ["rego", 2.98], ["soleo", 2.9], ["arbitrium", 2.81], ["numen", 2.81], ["regio", 2.79], ["iter", 2.78], ["similis", 2.73], ["uotum", 2.63], ["munio", 2.63], ["suscipio", 2.6], ["imperator", 2.57], ["utor", 2.57], ["saphrace", 2.45], ["frendo", 2.45], ["humanitas", 2.43], ["pulcher1", 2.43], ["excipio", 2.41], ["apex", 2.23], ["obsecro", 2.23]], "r16": [["species", 3.69], ["ito", 3.45], ["arbitrium", 3.44], ["numen", 3.44], ["rego", 3.44], ["histri", 3.32], ["uotum", 3.3], ["soleo", 3.2], ["saphrace", 3.16], ["margo", 3.16], ["offendo", 3.16], ["castellum", 3.15], ["celsus1", 3.15], ["munio", 3.14], ["excipio", 3.12], ["iter", 3.1], ["ctesiphontis", 3.0], ["utor", 2.91], ["alatheo", 2.83], ["exploro", 2.81], ["miror", 2.81], ["pulcher1", 2.8], ["regio", 2.78], ["similis", 2.69], ["apex", 2.64], ["suscipio", 2.58], ["audeo", 2.58], ["imperator", 2.54], ["uox", 2.54], ["frendo", 2.45], ["humanitas", 2.42], ["multitudo", 2.38], ["accedo", 2.37], ["orior", 2.36], ["antiochiam", 2.23], ["obsecro", 2.22], ["obscurus", 2.21]]}